{
  "version": "7",
  "dialect": "mysql",
  "entries": [
    {
      "idx": 0,
      "version": "5",
      "when": 1778013321883,
      "tag": "0000_fuzzy_dagger",
      "breakpoints": true
    },
    {
      "idx": 1,
      "version": "5",
      "when": 1778013370586,
      "tag": "0001_black_lady_deathstrike",
      "breakpoints": true
    },
    {
      "idx": 2,
      "version": "5",
      "when": 1778016882687,
      "tag": "0002_amazing_blue_marvel",
      "breakpoints": true
    },
    {
      "idx": 3,
      "version": "5",
      "when": 1778017237368,
      "tag": "0003_strange_the_professor",
      "breakpoints": true
    }
  ]
}